smartmutate/__init__.py
smartmutate/__main__.py
smartmutate/api.py
smartmutate/converter.py
smartmutate/engine.py
smartmutate/file_processor.py
smartmutate/loading_animation.py
smartmutate/registry.py
smartmutate-1.0.1.dist-info/LICENSE
smartmutate-1.0.1.dist-info/METADATA
smartmutate-1.0.1.dist-info/WHEEL
smartmutate-1.0.1.dist-info/entry_points.txt
smartmutate-1.0.1.dist-info/top_level.txt
smartmutate-1.0.1.dist-info/RECORD
