Metadata-Version: 2.2
Name: smartmutate
Version: 1.0.1
Summary: Use Anthropic Claude to convert files
Author-email: Spencer White <spence@sffw.dev>
Project-URL: Source Code, https://github.com/sffw/smartmutate
Classifier: Programming Language :: Python :: 3.8
Classifier: Operating System :: OS Independent
Requires-Python: >=3.7
License-File: LICENSE
Requires-Dist: click>=8.1.3
Requires-Dist: anthropic>=0.42.0
Requires-Dist: python-dotenv>=1.0.1
Requires-Dist: pandas>=2.1.0
Requires-Dist: pyyaml>=6.0.1
Provides-Extra: test
Requires-Dist: pytest>=8.3.4; extra == "test"
